__init__.py
inverted_encoding.py
inverted_encoding/__init__.py
package/__init__.py
package/inverted_encoding.py
src/__init__.py
src/inverted_encoding.py
inverted_encoding-0.2.3.dist-info/LICENSE.txt
inverted_encoding-0.2.3.dist-info/METADATA
inverted_encoding-0.2.3.dist-info/WHEEL
inverted_encoding-0.2.3.dist-info/top_level.txt
inverted_encoding-0.2.3.dist-info/RECORD
