Metadata-Version: 2.1
Name: inverted-encoding
Version: 0.2.3
Summary: Implementation of inverted encoding model as described in Scotti, Chen, & Golomb
Home-page: https://github.com/paulscotti/inverted_encoding
Author: Paul S. Scotti
Author-email: scottibrain@gmail.com
License: UNKNOWN
Platform: UNKNOWN
License-File: LICENSE.txt
Requires-Dist: numpy
